{
  "gitSyncId": "6760044ff8e58472f0a0be1b_d6e837b3-c138-4733-a820-45f2590c556d",
  "id": "Page2__$JSModule101$_JSModule10.reverseString",
  "isPublic": true,
  "moduleInstanceId": "Page2_JSModule101",
  "pluginId": "js-plugin",
  "pluginType": "JS",
  "rootModuleInstanceId": "Page2_JSModule101",
  "unpublishedAction": {
    "collectionId": "Page2__$JSModule101$_JSModule10",
    "confirmBeforeExecute": false,
    "contextType": "PAGE",
    "datasource": {
      "isAutoGenerated": false,
      "name": "UNUSED_DATASOURCE",
      "pluginId": "js-plugin"
    },
    "executeOnLoad": false,
    "fullyQualifiedName": "_$JSModule101$_JSModule10.reverseString",
    "name": "reverseString",
    "pageId": "Page2",
    "userSetOnLoad": false
  }
}