{
  "gitSyncId": "6760044ff8e58472f0a0be1b_443c6a70-7a7c-476f-afdd-cfbac6aa2d28",
  "id": "Page2 Copy1__$JSModule41$_JSModule4.addNumbers",
  "isPublic": true,
  "moduleInstanceId": "Page2 Copy1_JSModule41",
  "pluginId": "js-plugin",
  "pluginType": "JS",
  "rootModuleInstanceId": "Page2 Copy1_JSModule41",
  "unpublishedAction": {
    "collectionId": "Page2 Copy1__$JSModule41$_JSModule4",
    "confirmBeforeExecute": false,
    "contextType": "PAGE",
    "datasource": {
      "isAutoGenerated": false,
      "name": "UNUSED_DATASOURCE",
      "pluginId": "js-plugin"
    },
    "executeOnLoad": false,
    "fullyQualifiedName": "_$JSModule41$_JSModule4.addNumbers",
    "name": "addNumbers",
    "pageId": "Page2 Copy1",
    "userSetOnLoad": false
  }
}